frostbite_rcon_utils/__init__.py
frostbite_rcon_utils/decoder.py
frostbite_rcon_utils/encoder.py
frostbite_rcon_utils/helpers.py
frostbite_rcon_utils-2.0.0.dist-info/DESCRIPTION.rst
frostbite_rcon_utils-2.0.0.dist-info/METADATA
frostbite_rcon_utils-2.0.0.dist-info/RECORD
frostbite_rcon_utils-2.0.0.dist-info/WHEEL
frostbite_rcon_utils-2.0.0.dist-info/metadata.json
frostbite_rcon_utils-2.0.0.dist-info/top_level.txt
