Metadata-Version: 2.0
Name: frostbite-rcon-utils
Version: 2.0.0
Summary: A library that takes care of the encoding and decoding of packets sent to or from a Battlefield server (or any other server that uses their protocol).
Home-page: https://github.com/edvinerikson/frostbite-rcon-utils-python
Author: Edvin Erikson
Author-email: edvin@rocketblast.com
License: MIT
Download-URL: https://github.com/edvinerikson/frostbite-rcon-utils-python
Keywords: rcon battlefield frostbite protocol encode decode
Platform: Windows
Platform: Linux
Platform: Mac OS X
Classifier: Operating System :: OS Independent
Classifier: Programming Language :: Python
Classifier: Programming Language :: Python :: 2.7
